vquery/__init__.py
vquery/pchelper.py
vquery/vqconfig.py
vquery/vqconnect.py
vquery/vqcore.py
vquery-0.33.data/scripts/vq
vquery-0.33.dist-info/LICENSE.txt
vquery-0.33.dist-info/METADATA
vquery-0.33.dist-info/WHEEL
vquery-0.33.dist-info/top_level.txt
vquery-0.33.dist-info/RECORD
